metasyn/__init__.py
metasyn/__main__.py
metasyn/_version.py
metasyn/config.py
metasyn/file.py
metasyn/metaframe.py
metasyn/privacy.py
metasyn/py.typed
metasyn/registry.py
metasyn/testutils.py
metasyn/util.py
metasyn/validation.py
metasyn/var.py
metasyn/varspec.py
metasyn/demo/__init__.py
metasyn/demo/dataset.py
metasyn/demo/demo_druguse.csv
metasyn/demo/demo_fruit.csv
metasyn/demo/demo_hospital.csv
metasyn/demo/demo_spaceship.csv
metasyn/demo/demo_survey.csv
metasyn/demo/demo_synthea_imaging.csv
metasyn/demo/demo_test.csv
metasyn/demo/demo_titanic.csv
metasyn/distribution/__init__.py
metasyn/distribution/base.py
metasyn/distribution/categorical.py
metasyn/distribution/constant.py
metasyn/distribution/exponential.py
metasyn/distribution/faker.py
metasyn/distribution/freetext.py
metasyn/distribution/na.py
metasyn/distribution/normal.py
metasyn/distribution/poisson.py
metasyn/distribution/regex.py
metasyn/distribution/uniform.py
metasyn/distribution/uniquekey.py
metasyn/distribution/util.py
metasyn/schema/__init__.py
metasyn/schema/generative_metadata_format.json
metasyn/schema/plugin_registry.toml
metasyn-2.0.0.dist-info/LICENSE
metasyn-2.0.0.dist-info/METADATA
metasyn-2.0.0.dist-info/WHEEL
metasyn-2.0.0.dist-info/entry_points.txt
metasyn-2.0.0.dist-info/top_level.txt
metasyn-2.0.0.dist-info/RECORD
