Metadata-Version: 2.2
Name: metasyn
Version: 2.0.0
Summary: Package for creating synthetic datasets while preserving privacy.
Author-email: Raoul Schram <r.d.schram@uu.nl>, Erik-Jan van Kesteren <e.vankesteren1@uu.nl>
License: MIT License
Project-URL: GitHub, https://github.com/sodascience/metasyn
Project-URL: documentation, https://metasyn.readthedocs.io/en/latest/index.html
Keywords: metadata,open-data,privacy,synthetic-data,tabular datasets
Classifier: Programming Language :: Python :: 3
Classifier: Programming Language :: Python :: 3.10
Classifier: Programming Language :: Python :: 3.11
Classifier: Programming Language :: Python :: 3.12
Classifier: Programming Language :: Python :: 3.13
Classifier: Development Status :: 5 - Production/Stable
Classifier: License :: OSI Approved :: MIT License
Obsoletes: metasynth
Requires-Python: >=3.10
License-File: LICENSE
Requires-Dist: polars>=1
Requires-Dist: tqdm
Requires-Dist: numpy>=1.20; python_version < "3.12"
Requires-Dist: numpy>1.24.4; python_version >= "3.12"
Requires-Dist: pyarrow
Requires-Dist: scipy
Requires-Dist: faker
Requires-Dist: lingua-language-detector
Requires-Dist: regex
Requires-Dist: jsonschema
Requires-Dist: tomli; python_version < "3.11"
Requires-Dist: regexmodel>=0.2.1
Provides-Extra: extra
Requires-Dist: xlsxwriter; extra == "extra"
Requires-Dist: tomlkit; extra == "extra"
Requires-Dist: pyreadstat>=1.3; extra == "extra"
Requires-Dist: fastexcel; extra == "extra"
Provides-Extra: check
Requires-Dist: ruff; extra == "check"
Requires-Dist: mypy; extra == "check"
Requires-Dist: types-tqdm; extra == "check"
Requires-Dist: types-regex; extra == "check"
Provides-Extra: test
Requires-Dist: pytest; extra == "test"
Requires-Dist: nbval; extra == "test"
Requires-Dist: pytest-cov; extra == "test"
Requires-Dist: pandas; extra == "test"
Provides-Extra: docs
Requires-Dist: sphinx<9.0.0; extra == "docs"
Requires-Dist: sphinx-rtd-theme; extra == "docs"
Requires-Dist: sphinxcontrib-napoleon; extra == "docs"
Requires-Dist: sphinx-autodoc-typehints; extra == "docs"
Requires-Dist: sphinx_inline_tabs; extra == "docs"
Requires-Dist: sphinx_copybutton; extra == "docs"
Requires-Dist: sphinx-autobuild; extra == "docs"
Provides-Extra: dev
Requires-Dist: metasyn[check,docs,extra,test]; extra == "dev"
